[{"name":"rrd-xlsx-gateway","description":null,"location":"rrd-xlsx-gateway/index.html","searchKeys":["rrd-xlsx-gateway"]},{"name":"uk.co.ceilingcat.rrd.gateways.xlsxinputgateway","description":null,"location":"rrd-xlsx-gateway/uk.co.ceilingcat.rrd.gateways.xlsxinputgateway/index.html","searchKeys":["uk.co.ceilingcat.rrd.gateways.xlsxinputgateway"]},{"name":"createXlsxInputGateway()","description":null,"location":"rrd-xlsx-gateway/uk.co.ceilingcat.rrd.gateways.xlsxinputgateway/create-xlsx-input-gateway.html","searchKeys":["createXlsxInputGateway()"]},{"name":"StreetName","description":null,"location":"rrd-xlsx-gateway/uk.co.ceilingcat.rrd.gateways.xlsxinputgateway/-street-name/index.html","searchKeys":["StreetName"]},{"name":"WorkSheetsSearchDirectory","description":null,"location":"rrd-xlsx-gateway/uk.co.ceilingcat.rrd.gateways.xlsxinputgateway/-work-sheets-search-directory/index.html","searchKeys":["WorkSheetsSearchDirectory"]},{"name":"XlsxInputGateway","description":null,"location":"rrd-xlsx-gateway/uk.co.ceilingcat.rrd.gateways.xlsxinputgateway/-xlsx-input-gateway/index.html","searchKeys":["XlsxInputGateway"]},{"name":"XlsxInputGatewayException","description":null,"location":"rrd-xlsx-gateway/uk.co.ceilingcat.rrd.gateways.xlsxinputgateway/-xlsx-input-gateway-exception/index.html","searchKeys":["XlsxInputGatewayException"]}]
